README.md
requirements.txt
setup.cfg
setup.py
HupuApp.egg-info/PKG-INFO
HupuApp.egg-info/SOURCES.txt
HupuApp.egg-info/dependency_links.txt
HupuApp.egg-info/entry_points.txt
HupuApp.egg-info/requires.txt
HupuApp.egg-info/top_level.txt
hupu/__init__.py
hupu/hupuapp.py
hupu/hupulivewebsocket.py
hupu/utils.py
hupu/version.py
hupu/api/__init__.py
hupu/api/base.py
hupu/api/datas.py
hupu/api/forums.py
hupu/api/live.py
hupu/api/logger.py
hupu/api/login.py
hupu/api/news.py
hupu/menus/BaseMenu.py
hupu/menus/HupuMenu.py
hupu/menus/__init__.py
hupu/messages/__init__.py
hupu/messages/entries.py
hupu/messages/messages.py
test/test.py
test/testapi.py
test/testmain.py
test/testmenu.py
test/testmessage.py
test/testserver.py
test/testwindow.py