Metadata-Version: 1.2
Name: HupuApp
Version: 1.1.0
Summary: Proudly presented by Hupu JRs
Home-page: https://github.com/wudizhangzhi/HupuApp
Author: wudizhangzhi
Author-email: 554330595@qq.com
License: MIT
Keywords: hupu
Platform: UNKNOWN
Classifier: Development Status :: 3 - Alpha
Classifier: Programming Language :: Python :: 2
Classifier: Programming Language :: Python :: 3
Requires-Python: >=2.6,
